{
  "name": "Palmera Dao Token List for Somnia Chain",
  "timestamp": "2025-12-05T00:00:00.000Z",
  "version": {
    "major": 1,
    "minor": 0,
    "patch": 0
  },
  "tokens": [
    {
      "chainId": 5031,
      "address": "0x0000000000000000000000000000000000000000",
      "name": "Somi",
      "symbol": "SOMI",
      "decimals": 18,
      "logoURI": "https://coin-images.coingecko.com/coins/images/69031/large/somi.png?1757319530"
    },
    {
      "chainId": 5031,
      "address": "0x046EDe9564A72571df6F5e44d0405360c0f4dCab",
      "name": "Wrapped SOMI",
      "symbol": "WSOMI",
      "decimals": 18,
      "logoURI": "https://coin-images.coingecko.com/coins/images/69031/large/somi.png?1757319530"
    }
  ],
  "logoURI": "https://coin-images.coingecko.com/coins/images/69031/large/somi.png?1757319530",
  "tags": {
    "sourceList": {
      "name": "Palmera Dao Token List",
      "description": "Palmera Dao Token List, for Somnia Chain"
    }
  }
}
